[
    {
        "version": "OLD v1.0.0",
        "updateName": "Initial Release",
        "logLink": "updates/old-updates.md?parse=true#backup-google-chat-official-launch-(may-6th%2C-2021)"
    },
    {
        "version": "OLD v1.1.0",
        "updateName": "Archive Update",
        "logLink": "updates/old-updates.md?parse=true#archive-update-(may-7th%2C-2021)"
    },
    {
        "version": "OLD v1.2.0",
        "updateName": "Content Update 1",
        "logLink": "updates/old-updates.md?parse=true#content-update-1-(may-10th-or-11th%2C-2021)"
    },
    {
        "version": "OLD v1.3.0",
        "updateName": "Webhook Update",
        "logLink": "updates/old-updates.md?parse=true#webhook-update-(july-27th%2C-2021)"
    },
    {
        "version": "OLD v1.4.0",
        "updateName": "Authentication Update",
        "logLink": "updates/old-updates.md?parse=true#authentication-update-(july-29th%2C-2021)"
    },
    {
        "version": "OLD v1.5.0",
        "updateName": "Content Update 2",
        "logLink": "updates/old-updates.md?parse=true#content-update-2-(july-30th%2C-2021)"
    },
    {
        "version": "OLD v1.6.0",
        "updateName": "Image & Private Message Update",
        "logLink": "updates/old-updates.md?parse=true#image-%26-private-message-update-(august-2nd%2C-2021)"
    },
    {
        "version": "OLD v1.7.0",
        "updateName": "Edit and Delete Update",
        "logLink": "updates/old-updates.md?parse=true#edit-and-delete-update-(august-3rd%2C-2021)"
    },
    {
        "version": "OLD v1.8.0",
        "updateName": "Content Update 3",
        "logLink": "updates/old-updates.md?parse=true#content-update-3-(august-4th%2C-2021)"
    },
    {
        "version": "OLD v1.8.1",
        "updateName": "Content Update 3 Patch 1",
        "logLink": "updates/old-updates.md?parse=true#content-update-3-patch-1-(august-5th%2C-2021)"
    },
    {
        "version": "OLD v1.9.0",
        "updateName": "Direct Message Update",
        "logLink": "updates/old-updates.md?parse=true#direct-message-update-(october-24th%2C-2021)"
    },
    {
        "version": "OLD v1.9.1",
        "updateName": "Direct Message Update Patch 1",
        "logLink": "updates/old-updates.md?parse=true#direct-message-update-patch-1-(october-26th%2C-2021)"
    },
    {
        "version": "TIMELINE",
        "updateName": "Old Updates / Timeline",
        "logLink": "updates/old-updates.md?parse=true"
    },
    {
        "version": "NEW v1.0.0",
        "updateName": "Release of Update Logs / New Update Tracking",
        "logLink": "updates/update-tracking.md?parse=true"
    },
    {
        "version": "v1.1.0",
        "updateName": "Style Update",
        "logLink": "updates/2021.10.30.0s.pdf"
    },
    {
        "version": "v1.1.1",
        "updateName": "Style Update Patch 1",
        "logLink": "updates/2021.10.30.1s.pdf"
    },
    {
        "version": "v1.1.2",
        "updateName": "Style Update Patch 2",
        "logLink": "updates/2021.10.30.2s.pdf"
    },
    {
        "version": "v1.1.3",
        "updateName": "Style Update Patch 3",
        "logLink": "updates/2021.10.30.3s.pdf"
    },
    {
        "version": "v1.2.0",
        "updateName": "Search Update",
        "logLink": "updates/v1.2.0.md?parse=true"
    },
    {
        "version": "v1.2.1",
        "updateName": "Ukraine Update / Search Update Patch 1",
        "logLink": "updates/v1.2.1.md?parse=true"
    },
    {
        "version": "v1.2.2",
        "updateName": "Search Update Patch 2",
        "logLink": "updates/v1.2.2.md?parse=true"
    },
    {
        "version": "v1.3.0",
        "updateName": "Optimization Update",
        "logLink": "updates/v1.3.0.md?parse=true"
    },
    {
        "version": "v1.3.1",
        "updateName": "Optimization Update Patch 1",
        "logLink": "updates/v1.3.1.md?parse=true"
    },
    {
        "version": "v1.3.2",
        "updateName": "Optimization Update Patch 2",
        "logLink": "updates/v1.3.2.md?parse=true"
    },
    {
        "version": "v1.3.3",
        "updateName": "Optimization Update Patch 3",
        "logLink": "updates/v1.3.3.md?parse=true"
    },
    {
        "version": "v1.4.0",
        "updateName": "Account Update",
        "logLink": "updates/v1.4.0.md?parse=true"
    },
    {
        "version": "v1.4.1",
        "updateName": "Account Update Patch 1",
        "logLink": "updates/v1.4.1.md?parse=true"
    },
    {
        "version": "v1.5.0",
        "updateName": "Quality of Life Update",
        "logLink": "updates/v1.5.0.md?parse=true"
    },
    {
        "version": "v1.5.1",
        "updateName": "Quality of Life Update Patch 1",
        "logLink": "updates/v1.5.1.md?parse=true"
    }
]